tensorboard_reporter/__init__.py
tensorboard_reporter/loader.py
tensorboard_reporter/stats.py
tensorboard_reporter/summary.py
tensorboard_reporter-0.0.5.data/scripts/tensorboard-reporter
tensorboard_reporter-0.0.5.dist-info/LICENSE
tensorboard_reporter-0.0.5.dist-info/METADATA
tensorboard_reporter-0.0.5.dist-info/WHEEL
tensorboard_reporter-0.0.5.dist-info/top_level.txt
tensorboard_reporter-0.0.5.dist-info/RECORD
