Metadata-Version: 2.1
Name: tensorboard-reporter
Version: 0.0.5
Summary: Get reports for your training process via Slack
Home-page: https://github.com/unexge/tensorboard-reporter
Author: unexge
Author-email: unexge@gmail.com
License: UNKNOWN
Platform: UNKNOWN
Classifier: Programming Language :: Python :: 3
Classifier: License :: OSI Approved :: MIT License
Classifier: Operating System :: OS Independent
Requires-Python: >=3.6
Requires-Dist: slack
Requires-Dist: slackclient
Requires-Dist: tensorflow
Requires-Dist: numpy
Requires-Dist: tqdm
